README.rst
setup.py
timeme/__init__.py
timeme/timeme.py
timeme.egg-info/PKG-INFO
timeme.egg-info/SOURCES.txt
timeme.egg-info/dependency_links.txt
timeme.egg-info/top_level.txt