Metadata-Version: 1.0
Name: timeme
Version: 0.1.1
Summary: Decorator that prints the running time of a function
Home-page: http://github.com/enricobacis/timeme
Author: Enrico Bacis
Author-email: enrico.bacis@gmail.com
License: MIT
Keywords: time timing function decorator
Platform: UNKNOWN
